{
  "0": {
    "n": 1999,
    "organ": "leaf (1257)",
    "order": "Poales (1794)",
    "family": "Poaceae (1794)",
    "species": "Zea mays (959)"
  },
  "1": {
    "n": 1075,
    "organ": "leaf (752)",
    "order": "Vitales (1050)",
    "family": "Vitaceae (1050)",
    "species": "Vitis vinifera (889)"
  },
  "2": {
    "n": 2542,
    "organ": "leaf (787)",
    "order": "Poales (1863)",
    "family": "Poaceae (1863)",
    "species": "Zea mays (1407)"
  },
  "3": {
    "n": 2261,
    "organ": "leaf (943)",
    "order": "Brassicales (1431)",
    "family": "Brassicaceae (1431)",
    "species": "Arabidopsis thaliana (1207)"
  },
  "4": {
    "n": 2346,
    "organ": "leaf (1982)",
    "order": "Poales (608)",
    "family": "Poaceae (608)",
    "species": "Oloptum miliaceum (826)"
  },
  "5": {
    "n": 2551,
    "organ": "flower (651)",
    "order": "Proteales (30)",
    "family": "Proteaceae (30)",
    "species": "Persea americana (289)"
  },
  "6": {
    "n": 3335,
    "organ": "leaf (2381)",
    "order": "Solanales (2949)",
    "family": "Solanaceae (2949)",
    "species": "Nicotiana tabacum (2018)"
  },
  "7": {
    "n": 1583,
    "organ": "flower (379)",
    "order": "Poales (1)",
    "family": "Poaceae (1)",
    "species": "Musa acuminata AAA Group (103)"
  },
  "8": {
    "n": 4359,
    "organ": "leaf (1288)",
    "order": "Brassicales (1047)",
    "family": "Brassicaceae (1033)",
    "species": "Arabidopsis thaliana (843)"
  },
  "9": {
    "n": 3907,
    "organ": "leaf (2287)",
    "order": "Poales (3670)",
    "family": "Poaceae (3670)",
    "species": "Oryza sativa (2221)"
  },
  "10": {
    "n": 4004,
    "organ": "leaf (3418)",
    "order": "Myrtales (98)",
    "family": "Myrtaceae (98)",
    "species": "Litchi chinensis (148)"
  },
  "11": {
    "n": 6365,
    "organ": "whole-plant (4045)",
    "order": "Brassicales (5794)",
    "family": "Brassicaceae (5794)",
    "species": "Arabidopsis thaliana (5610)"
  },
  "12": {
    "n": 1936,
    "organ": "leaf (1088)",
    "order": "Poales (1727)",
    "family": "Poaceae (1727)",
    "species": "Triticum aestivum (872)"
  },
  "13": {
    "n": 4884,
    "organ": "root (1033)",
    "order": "mixed",
    "family": "mixed",
    "species": "Allium sativum (384)"
  },
  "14": {
    "n": 710,
    "organ": "leaf (148)",
    "order": "Poales (145)",
    "family": "Poaceae (145)",
    "species": "Triticum aestivum (60)"
  },
  "15": {
    "n": 2964,
    "organ": "leaf (815)",
    "order": "Brassicales (2710)",
    "family": "Brassicaceae (2710)",
    "species": "Arabidopsis thaliana (2605)"
  },
  "16": {
    "n": 2283,
    "organ": "leaf (1221)",
    "order": "Poales (1450)",
    "family": "Poaceae (1450)",
    "species": "Sorghum bicolor (1291)"
  },
  "17": {
    "n": 1302,
    "organ": "root (477)",
    "order": "Poales (1207)",
    "family": "Poaceae (1207)",
    "species": "Hordeum vulgare (419)"
  },
  "18": {
    "n": 1490,
    "organ": "root (635)",
    "order": "Fabales (1201)",
    "family": "Fabaceae (1201)",
    "species": "Arachis hypogaea (1091)"
  },
  "19": {
    "n": 2349,
    "organ": "leaf (1876)",
    "order": "Asterales (1137)",
    "family": "Asteraceae (1137)",
    "species": "Lactuca sativa (542)"
  },
  "20": {
    "n": 3917,
    "organ": "stem (968)",
    "order": "Pinales (2838)",
    "family": "Pinaceae (2838)",
    "species": "Picea abies (524)"
  },
  "21": {
    "n": 3084,
    "organ": "stem (869)",
    "order": "Apiales (91)",
    "family": "Apiaceae (91)",
    "species": "Cannabis sativa (269)"
  },
  "22": {
    "n": 6149,
    "organ": "leaf (4824)",
    "order": "Brassicales (5720)",
    "family": "Brassicaceae (5719)",
    "species": "Brassica napus (2263)"
  },
  "23": {
    "n": 2391,
    "organ": "whole-plant (270)",
    "order": "mixed",
    "family": "mixed",
    "species": "Chlamydomonas reinhardtii (1315)"
  },
  "24": {
    "n": 1949,
    "organ": "flower (649)",
    "order": "Poales (1751)",
    "family": "Poaceae (1751)",
    "species": "Triticum aestivum (1470)"
  },
  "25": {
    "n": 1149,
    "organ": "flower (183)",
    "order": "Poales (1099)",
    "family": "Poaceae (1099)",
    "species": "Zea mays (449)"
  },
  "26": {
    "n": 2171,
    "organ": "fruit (590)",
    "order": "Rosales (154)",
    "family": "Rosaceae (154)",
    "species": "Actinidia chinensis (95)"
  },
  "27": {
    "n": 3136,
    "organ": "root (1290)",
    "order": "Myrtales (323)",
    "family": "Myrtaceae (323)",
    "species": "Quercus robur (266)"
  },
  "28": {
    "n": 1764,
    "organ": "seed (814)",
    "order": "Fabales (838)",
    "family": "Fabaceae (838)",
    "species": "Glycine max (818)"
  },
  "29": {
    "n": 8692,
    "organ": "root (6253)",
    "order": "Brassicales (8506)",
    "family": "Brassicaceae (8501)",
    "species": "Arabidopsis thaliana (7824)"
  },
  "30": {
    "n": 3424,
    "organ": "leaf (2819)",
    "order": "Poales (3237)",
    "family": "Poaceae (3237)",
    "species": "Triticum aestivum (2709)"
  },
  "31": {
    "n": 1740,
    "organ": "leaf (536)",
    "order": "Solanales (1555)",
    "family": "Solanaceae (1555)",
    "species": "Solanum lycopersicum (597)"
  },
  "32": {
    "n": 2839,
    "organ": "root (522)",
    "order": "Brassicales (494)",
    "family": "Brassicaceae (492)",
    "species": "Arabidopsis thaliana (413)"
  },
  "33": {
    "n": 1407,
    "organ": "root (289)",
    "order": "Solanales (1351)",
    "family": "Solanaceae (1351)",
    "species": "Solanum lycopersicum (1078)"
  },
  "34": {
    "n": 1839,
    "organ": "root (1190)",
    "order": "Malpighiales (1754)",
    "family": "Euphorbiaceae (1754)",
    "species": "Manihot esculenta (1337)"
  },
  "35": {
    "n": 3014,
    "organ": "leaf (2275)",
    "order": "Fabales (2323)",
    "family": "Fabaceae (2323)",
    "species": "Glycine max (1181)"
  },
  "36": {
    "n": 2474,
    "organ": "flower (1268)",
    "order": "Poales (2299)",
    "family": "Poaceae (2299)",
    "species": "Oryza sativa (1414)"
  },
  "37": {
    "n": 4530,
    "organ": "root (3537)",
    "order": "Solanales (4257)",
    "family": "Solanaceae (4257)",
    "species": "Solanum lycopersicum (1778)"
  },
  "38": {
    "n": 1508,
    "organ": "root (987)",
    "order": "Poales (1130)",
    "family": "Poaceae (1130)",
    "species": "Zea mays (605)"
  },
  "39": {
    "n": 1424,
    "organ": "stem (390)",
    "order": "Malpighiales (1330)",
    "family": "Salicaceae (1330)",
    "species": "Populus nigra (503)"
  },
  "40": {
    "n": 546,
    "organ": "whole-plant (310)",
    "order": "Selaginellales (209)",
    "family": "Selaginellaceae (209)",
    "species": "Selaginella moellendorffii (109)"
  },
  "41": {
    "n": 786,
    "organ": "leaf (417)",
    "order": "Malpighiales (786)",
    "family": "Salicaceae (786)",
    "species": "Populus trichocarpa (750)"
  },
  "42": {
    "n": 1213,
    "organ": "flower (525)",
    "order": "Malvales (935)",
    "family": "Malvaceae (935)",
    "species": "Gossypium hirsutum (624)"
  },
  "43": {
    "n": 1801,
    "organ": "root (1292)",
    "order": "Brassicales (1443)",
    "family": "Brassicaceae (1442)",
    "species": "Arabidopsis thaliana (1396)"
  },
  "44": {
    "n": 3217,
    "organ": "flower (688)",
    "order": "Poales (2770)",
    "family": "Poaceae (2770)",
    "species": "Zea mays (2647)"
  },
  "45": {
    "n": 2193,
    "organ": "flower (1241)",
    "order": "Poales (2110)",
    "family": "Poaceae (2110)",
    "species": "Triticum aestivum (934)"
  },
  "46": {
    "n": 1580,
    "organ": "fruit (1088)",
    "order": "Poales (1580)",
    "family": "Poaceae (1580)",
    "species": "Zea mays (1580)"
  },
  "47": {
    "n": 1348,
    "organ": "seed (846)",
    "order": "Poales (1225)",
    "family": "Poaceae (1225)",
    "species": "Setaria italica (563)"
  },
  "48": {
    "n": 2647,
    "organ": "leaf (2086)",
    "order": "Gentianales (52)",
    "family": "Rubiaceae (43)",
    "species": "Rumex hastatulus (581)"
  },
  "49": {
    "n": 5223,
    "organ": "whole-plant (1325)",
    "order": "Brassicales (1566)",
    "family": "Brassicaceae (1566)",
    "species": "Arabidopsis thaliana (996)"
  },
  "50": {
    "n": 5046,
    "organ": "leaf (4198)",
    "order": "Poales (4919)",
    "family": "Poaceae (4919)",
    "species": "Zea mays (4818)"
  },
  "51": {
    "n": 1106,
    "organ": "leaf (383)",
    "order": "Brassicales (1073)",
    "family": "Brassicaceae (1073)",
    "species": "Arabidopsis thaliana (979)"
  },
  "52": {
    "n": 691,
    "organ": "leaf (381)",
    "order": "Poales (691)",
    "family": "Poaceae (691)",
    "species": "Hordeum vulgare (388)"
  },
  "53": {
    "n": 2356,
    "organ": "root (1882)",
    "order": "Poales (1263)",
    "family": "Poaceae (1263)",
    "species": "Sorghum bicolor (686)"
  },
  "54": {
    "n": 3153,
    "organ": "leaf (2614)",
    "order": "Fabales (2944)",
    "family": "Fabaceae (2944)",
    "species": "Glycine max (2157)"
  },
  "55": {
    "n": 2098,
    "organ": "leaf (712)",
    "order": "Rosales (439)",
    "family": "Rosaceae (439)",
    "species": "Vitis vinifera (265)"
  },
  "56": {
    "n": 2505,
    "organ": "fruit (673)",
    "order": "Cucurbitales (2203)",
    "family": "Cucurbitaceae (2203)",
    "species": "Cucumis sativus (1007)"
  },
  "57": {
    "n": 5590,
    "organ": "leaf (3901)",
    "order": "Brassicales (5345)",
    "family": "Brassicaceae (5345)",
    "species": "Arabidopsis thaliana (5075)"
  },
  "58": {
    "n": 3476,
    "organ": "leaf (902)",
    "order": "Brassicales (2555)",
    "family": "Brassicaceae (2553)",
    "species": "Arabidopsis thaliana (2361)"
  },
  "59": {
    "n": 1705,
    "organ": "fruit (614)",
    "order": "Rosales (1637)",
    "family": "Rosaceae (1637)",
    "species": "Prunus persica (677)"
  },
  "60": {
    "n": 3120,
    "organ": "fruit (1027)",
    "order": "Rosales (2775)",
    "family": "Rosaceae (2775)",
    "species": "Malus domestica (1255)"
  },
  "61": {
    "n": 2721,
    "organ": "leaf (1540)",
    "order": "Poales (2118)",
    "family": "Poaceae (2118)",
    "species": "Zea mays (798)"
  },
  "62": {
    "n": 2438,
    "organ": "leaf (1008)",
    "order": "Brassicales (2276)",
    "family": "Brassicaceae (2276)",
    "species": "Arabidopsis thaliana (1927)"
  },
  "63": {
    "n": 1945,
    "organ": "leaf (1820)",
    "order": "mixed",
    "family": "mixed",
    "species": "Erythranthe guttata (1945)"
  },
  "64": {
    "n": 620,
    "organ": "leaf (592)",
    "order": "Poales (612)",
    "family": "Poaceae (612)",
    "species": "Oryza sativa (579)"
  },
  "65": {
    "n": 607,
    "organ": "leaf (258)",
    "order": "Fabales (568)",
    "family": "Fabaceae (568)",
    "species": "Glycine max (568)"
  },
  "66": {
    "n": 3447,
    "organ": "leaf (2522)",
    "order": "Solanales (3242)",
    "family": "Solanaceae (3242)",
    "species": "Solanum lycopersicum (2966)"
  },
  "67": {
    "n": 2707,
    "organ": "leaf (2126)",
    "order": "Ericales (207)",
    "family": "Theaceae (207)",
    "species": "Cornus florida (230)"
  },
  "68": {
    "n": 4642,
    "organ": "flower (1501)",
    "order": "Brassicales (121)",
    "family": "Euphorbiaceae (105)",
    "species": "Litchi chinensis (187)"
  },
  "69": {
    "n": 5409,
    "organ": "stem (1659)",
    "order": "Poales (4189)",
    "family": "Poaceae (4189)",
    "species": "Zea mays (3381)"
  },
  "70": {
    "n": 2868,
    "organ": "seed (1097)",
    "order": "Brassicales (2661)",
    "family": "Brassicaceae (2650)",
    "species": "Brassica napus (1660)"
  },
  "71": {
    "n": 3326,
    "organ": "stem (1216)",
    "order": "Poales (2964)",
    "family": "Poaceae (2964)",
    "species": "Hordeum vulgare (1056)"
  },
  "72": {
    "n": 2351,
    "organ": "leaf (1503)",
    "order": "Poales (1730)",
    "family": "Poaceae (1730)",
    "species": "Triticum aestivum (542)"
  },
  "73": {
    "n": 2400,
    "organ": "leaf (1641)",
    "order": "Lamiales (4)",
    "family": "Oleaceae (4)",
    "species": "Zostera marina (286)"
  },
  "74": {
    "n": 2869,
    "organ": "fruit (1434)",
    "order": "Lamiales (48)",
    "family": "Oleaceae (48)",
    "species": "Diospyros kaki (395)"
  },
  "75": {
    "n": 2204,
    "organ": "leaf (653)",
    "order": "Fabales (119)",
    "family": "Fabaceae (119)",
    "species": "Fraxinus excelsior (132)"
  },
  "76": {
    "n": 1593,
    "organ": "flower (634)",
    "order": "Poales (1506)",
    "family": "Poaceae (1506)",
    "species": "Hordeum vulgare (764)"
  },
  "77": {
    "n": 2617,
    "organ": "root (2040)",
    "order": "Fabales (1264)",
    "family": "Fabaceae (1264)",
    "species": "Lotus japonicus (682)"
  },
  "78": {
    "n": 4738,
    "organ": "leaf (3282)",
    "order": "Poales (4077)",
    "family": "Poaceae (4077)",
    "species": "Oryza sativa (2689)"
  },
  "79": {
    "n": 3882,
    "organ": "leaf (2978)",
    "order": "Poales (3626)",
    "family": "Poaceae (3626)",
    "species": "Oryza sativa (2543)"
  },
  "80": {
    "n": 3026,
    "organ": "leaf (452)",
    "order": "Malvales (2997)",
    "family": "Malvaceae (2997)",
    "species": "Gossypium hirsutum (2370)"
  },
  "81": {
    "n": 1877,
    "organ": "seed (1102)",
    "order": "Brassicales (1820)",
    "family": "Brassicaceae (1817)",
    "species": "Brassica napus (733)"
  },
  "82": {
    "n": 3349,
    "organ": "root (2596)",
    "order": "Poales (3269)",
    "family": "Poaceae (3269)",
    "species": "Zea mays (3165)"
  },
  "83": {
    "n": 3318,
    "organ": "leaf (2478)",
    "order": "Malpighiales (3044)",
    "family": "Salicaceae (3044)",
    "species": "Populus trichocarpa (452)"
  },
  "84": {
    "n": 1858,
    "organ": "leaf (803)",
    "order": "mixed",
    "family": "mixed",
    "species": "Fagopyrum tataricum (257)"
  },
  "85": {
    "n": 2646,
    "organ": "root (2081)",
    "order": "Poales (2435)",
    "family": "Poaceae (2435)",
    "species": "Triticum aestivum (2183)"
  },
  "86": {
    "n": 1459,
    "organ": "whole-plant (925)",
    "order": "Fabales (1369)",
    "family": "Fabaceae (1369)",
    "species": "Arachis hypogaea (1340)"
  },
  "87": {
    "n": 2264,
    "organ": "stem (2173)",
    "order": "Brassicales (2263)",
    "family": "Brassicaceae (2263)",
    "species": "Brassica napus (2180)"
  },
  "88": {
    "n": 2473,
    "organ": "flower (469)",
    "order": "Brassicales (386)",
    "family": "Brassicaceae (381)",
    "species": "Arabidopsis thaliana (268)"
  },
  "89": {
    "n": 2180,
    "organ": "whole-plant (1378)",
    "order": "Brassicales (1937)",
    "family": "Brassicaceae (1937)",
    "species": "Arabidopsis thaliana (1854)"
  },
  "90": {
    "n": 425,
    "organ": "fruit (419)",
    "order": "Vitales (425)",
    "family": "Vitaceae (425)",
    "species": "Vitis labrusca x Vitis vinifera (198)"
  },
  "91": {
    "n": 2462,
    "organ": "leaf (1311)",
    "order": "Ericales (2388)",
    "family": "Theaceae (2388)",
    "species": "Camellia sinensis (1739)"
  },
  "92": {
    "n": 3197,
    "organ": "leaf (1370)",
    "order": "Poales (2262)",
    "family": "Poaceae (2262)",
    "species": "Avena sativa (559)"
  },
  "93": {
    "n": 1700,
    "organ": "leaf (1277)",
    "order": "Vitales (1689)",
    "family": "Vitaceae (1689)",
    "species": "Vitis vinifera (1667)"
  },
  "94": {
    "n": 1944,
    "organ": "leaf (1037)",
    "order": "Poales (1925)",
    "family": "Poaceae (1925)",
    "species": "Sorghum bicolor (800)"
  },
  "95": {
    "n": 4229,
    "organ": "root (918)",
    "order": "Pinales (3052)",
    "family": "Pinaceae (3052)",
    "species": "Picea abies (843)"
  },
  "96": {
    "n": 1340,
    "organ": "leaf (1076)",
    "order": "Malvales (1037)",
    "family": "Malvaceae (1037)",
    "species": "Gossypium hirsutum (786)"
  },
  "97": {
    "n": 3029,
    "organ": "leaf (1522)",
    "order": "Caryophyllales (2)",
    "family": "Amaranthaceae (2)",
    "species": "Lilium brownii (141)"
  },
  "98": {
    "n": 679,
    "organ": "stem (105)",
    "order": "Poales (292)",
    "family": "Poaceae (292)",
    "species": "Zea mays (223)"
  },
  "99": {
    "n": 2729,
    "organ": "whole-plant (566)",
    "order": "Brassicales (1975)",
    "family": "Brassicaceae (1975)",
    "species": "Arabidopsis thaliana (1716)"
  },
  "100": {
    "n": 4112,
    "organ": "root (3001)",
    "order": "Poales (4036)",
    "family": "Poaceae (4036)",
    "species": "Oryza sativa (2047)"
  },
  "101": {
    "n": 4581,
    "organ": "flower (1449)",
    "order": "Solanales (3923)",
    "family": "Solanaceae (3923)",
    "species": "Solanum lycopersicum (2082)"
  },
  "102": {
    "n": 1437,
    "organ": "root (401)",
    "order": "Caryophyllales (897)",
    "family": "Amaranthaceae (897)",
    "species": "Beta vulgaris subsp. vulgaris (309)"
  },
  "103": {
    "n": 2654,
    "organ": "flower (1006)",
    "order": "Asterales (1078)",
    "family": "Asteraceae (1078)",
    "species": "Chrysanthemum x morifolium (417)"
  },
  "104": {
    "n": 4339,
    "organ": "whole-plant (3354)",
    "order": "Brassicales (4057)",
    "family": "Brassicaceae (4057)",
    "species": "Arabidopsis thaliana (3885)"
  },
  "105": {
    "n": 2978,
    "organ": "root (2005)",
    "order": "Brassicales (2780)",
    "family": "Brassicaceae (2780)",
    "species": "Brassica napus (1320)"
  },
  "106": {
    "n": 1757,
    "organ": "root (599)",
    "order": "Ericales (1129)",
    "family": "Theaceae (1129)",
    "species": "Camellia sinensis (548)"
  },
  "107": {
    "n": 2385,
    "organ": "whole-plant (523)",
    "order": "Brassicales (2199)",
    "family": "Brassicaceae (2199)",
    "species": "Arabidopsis thaliana (2094)"
  },
  "108": {
    "n": 569,
    "organ": "flower (72)",
    "order": "Poales (518)",
    "family": "Poaceae (518)",
    "species": "Zea mays (264)"
  },
  "109": {
    "n": 1563,
    "organ": "seed (441)",
    "order": "Poales (1332)",
    "family": "Poaceae (1332)",
    "species": "Oryza sativa (812)"
  },
  "110": {
    "n": 1459,
    "organ": "whole-plant (1174)",
    "order": "Brassicales (550)",
    "family": "Brassicaceae (541)",
    "species": "Arabidopsis thaliana (465)"
  },
  "111": {
    "n": 2736,
    "organ": "leaf (1746)",
    "order": "Fabales (1833)",
    "family": "Fabaceae (1833)",
    "species": "Medicago truncatula (401)"
  },
  "112": {
    "n": 1897,
    "organ": "leaf (827)",
    "order": "Poales (1662)",
    "family": "Poaceae (1662)",
    "species": "Zea mays (1507)"
  },
  "113": {
    "n": 3948,
    "organ": "fruit (3015)",
    "order": "Vitales (3640)",
    "family": "Vitaceae (3640)",
    "species": "Vitis vinifera (3261)"
  },
  "114": {
    "n": 583,
    "organ": "mixed",
    "order": "mixed",
    "family": "mixed",
    "species": "Micromonas commoda (65)"
  },
  "115": {
    "n": 1799,
    "organ": "root (1378)",
    "order": "Caryophyllales (513)",
    "family": "Amaranthaceae (513)",
    "species": "Beta vulgaris (198)"
  },
  "116": {
    "n": 2569,
    "organ": "leaf (1841)",
    "order": "Solanales (956)",
    "family": "Solanaceae (956)",
    "species": "Nicotiana attenuata (349)"
  },
  "117": {
    "n": 3104,
    "organ": "stem (1267)",
    "order": "Poales (2206)",
    "family": "Poaceae (2206)",
    "species": "Sorghum bicolor (1870)"
  },
  "118": {
    "n": 2019,
    "organ": "leaf (1673)",
    "order": "Ericales (1935)",
    "family": "Theaceae (1935)",
    "species": "Camellia sinensis (1273)"
  },
  "119": {
    "n": 4697,
    "organ": "leaf (3046)",
    "order": "Brassicales (4267)",
    "family": "Brassicaceae (4266)",
    "species": "Brassica napus (1967)"
  },
  "120": {
    "n": 1926,
    "organ": "seed (1393)",
    "order": "Fabales (1764)",
    "family": "Fabaceae (1764)",
    "species": "Glycine max (1495)"
  },
  "121": {
    "n": 2837,
    "organ": "flower (1987)",
    "order": "Malvales (2780)",
    "family": "Malvaceae (2780)",
    "species": "Gossypium hirsutum (2203)"
  },
  "122": {
    "n": 2647,
    "organ": "leaf (936)",
    "order": "Brassicales (2227)",
    "family": "Brassicaceae (2224)",
    "species": "Arabidopsis thaliana (1889)"
  },
  "123": {
    "n": 3536,
    "organ": "fruit (2981)",
    "order": "Solanales (3527)",
    "family": "Solanaceae (3527)",
    "species": "Solanum lycopersicum (3370)"
  },
  "124": {
    "n": 1633,
    "organ": "stem (1124)",
    "order": "Poales (1633)",
    "family": "Poaceae (1633)",
    "species": "Zea mays (1531)"
  },
  "125": {
    "n": 1290,
    "organ": "leaf (481)",
    "order": "Brassicales (1115)",
    "family": "Brassicaceae (1112)",
    "species": "Arabidopsis thaliana (967)"
  },
  "126": {
    "n": 2722,
    "organ": "leaf (1790)",
    "order": "Solanales (2455)",
    "family": "Solanaceae (2455)",
    "species": "Solanum tuberosum (1361)"
  },
  "127": {
    "n": 2228,
    "organ": "stem (721)",
    "order": "Malpighiales (1892)",
    "family": "Salicaceae (1892)",
    "species": "Populus trichocarpa (271)"
  },
  "128": {
    "n": 2610,
    "organ": "leaf (1983)",
    "order": "Cucurbitales (2146)",
    "family": "Cucurbitaceae (2146)",
    "species": "Cucumis sativus (1102)"
  },
  "129": {
    "n": 1133,
    "organ": "stem (488)",
    "order": "Poales (962)",
    "family": "Poaceae (962)",
    "species": "Saccharum hybrid cultivar (540)"
  },
  "130": {
    "n": 2064,
    "organ": "leaf (1390)",
    "order": "Poales (1825)",
    "family": "Poaceae (1825)",
    "species": "Oryza sativa Japonica Group (851)"
  },
  "131": {
    "n": 3285,
    "organ": "fruit (912)",
    "order": "Malpighiales (60)",
    "family": "Euphorbiaceae (60)",
    "species": "Fagus sylvatica (211)"
  },
  "132": {
    "n": 1750,
    "organ": "seed (758)",
    "order": "Poales (1696)",
    "family": "Poaceae (1696)",
    "species": "Zea mays (1495)"
  },
  "133": {
    "n": 2724,
    "organ": "leaf (2163)",
    "order": "Poales (1118)",
    "family": "Poaceae (1118)",
    "species": "Setaria italica (355)"
  },
  "134": {
    "n": 3606,
    "organ": "stem (1318)",
    "order": "Poales (1465)",
    "family": "Poaceae (1465)",
    "species": "Phyllostachys edulis (352)"
  },
  "135": {
    "n": 4574,
    "organ": "whole-plant (2202)",
    "order": "Brassicales (3542)",
    "family": "Brassicaceae (3542)",
    "species": "Arabidopsis thaliana (3392)"
  },
  "136": {
    "n": 2566,
    "organ": "leaf (925)",
    "order": "Poales (767)",
    "family": "Poaceae (767)",
    "species": "Triticum aestivum (315)"
  },
  "137": {
    "n": 946,
    "organ": "whole-plant (901)",
    "order": "Brassicales (946)",
    "family": "Brassicaceae (946)",
    "species": "Arabidopsis thaliana (944)"
  },
  "138": {
    "n": 2018,
    "organ": "leaf (1499)",
    "order": "Asterales (1304)",
    "family": "Asteraceae (1304)",
    "species": "Lactuca sativa (487)"
  },
  "139": {
    "n": 2098,
    "organ": "root (807)",
    "order": "mixed",
    "family": "mixed",
    "species": "Musa acuminata AAA Group (317)"
  },
  "140": {
    "n": 1357,
    "organ": "leaf (1031)",
    "order": "Poales (1129)",
    "family": "Poaceae (1129)",
    "species": "Triticum aestivum (763)"
  },
  "141": {
    "n": 3183,
    "organ": "flower (1424)",
    "order": "Brassicales (2992)",
    "family": "Brassicaceae (2979)",
    "species": "Arabidopsis thaliana (2620)"
  },
  "142": {
    "n": 3845,
    "organ": "leaf (2906)",
    "order": "Lamiales (218)",
    "family": "Oleaceae (116)",
    "species": "Erythranthe guttata (424)"
  },
  "143": {
    "n": 3990,
    "organ": "stem (1617)",
    "order": "Poales (3848)",
    "family": "Poaceae (3848)",
    "species": "Oryza sativa (2140)"
  },
  "144": {
    "n": 2180,
    "organ": "leaf (1367)",
    "order": "Poales (2027)",
    "family": "Poaceae (2027)",
    "species": "Hordeum vulgare (975)"
  },
  "145": {
    "n": 2792,
    "organ": "fruit (969)",
    "order": "Poales (2522)",
    "family": "Poaceae (2522)",
    "species": "Triticum aestivum (1617)"
  },
  "146": {
    "n": 3085,
    "organ": "leaf (1934)",
    "order": "Apiales (112)",
    "family": "Apiaceae (112)",
    "species": "Panax notoginseng (171)"
  },
  "147": {
    "n": 1855,
    "organ": "leaf (1193)",
    "order": "Malvales (1650)",
    "family": "Malvaceae (1650)",
    "species": "Gossypium hirsutum (1124)"
  },
  "148": {
    "n": 1709,
    "organ": "whole-plant (865)",
    "order": "Selaginellales (36)",
    "family": "Selaginellaceae (36)",
    "species": "Ceratopteris richardii (234)"
  },
  "149": {
    "n": 799,
    "organ": "cell-culture (414)",
    "order": "Brassicales (772)",
    "family": "Brassicaceae (772)",
    "species": "Arabidopsis thaliana (650)"
  },
  "150": {
    "n": 1235,
    "organ": "root (986)",
    "order": "Cucurbitales (1109)",
    "family": "Cucurbitaceae (1109)",
    "species": "Cucumis sativus (581)"
  },
  "151": {
    "n": 2865,
    "organ": "leaf (2377)",
    "order": "mixed",
    "family": "mixed",
    "species": "Cocos nucifera (130)"
  },
  "152": {
    "n": 3225,
    "organ": "whole-plant (962)",
    "order": "Brassicales (3150)",
    "family": "Brassicaceae (3150)",
    "species": "Arabidopsis thaliana (3146)"
  },
  "153": {
    "n": 2742,
    "organ": "fruit (1102)",
    "order": "Malpighiales (21)",
    "family": "Euphorbiaceae (21)",
    "species": "Ziziphus jujuba (355)"
  },
  "154": {
    "n": 2176,
    "organ": "flower (822)",
    "order": "Proteales (61)",
    "family": "Proteaceae (61)",
    "species": "Nelumbo nucifera (174)"
  },
  "155": {
    "n": 2715,
    "organ": "stem (388)",
    "order": "Malpighiales (2081)",
    "family": "Salicaceae (2081)",
    "species": "Populus trichocarpa (766)"
  },
  "156": {
    "n": 2270,
    "organ": "stem (740)",
    "order": "Poales (2222)",
    "family": "Poaceae (2222)",
    "species": "Zea mays (1325)"
  },
  "157": {
    "n": 960,
    "organ": "seed (688)",
    "order": "Fabales (609)",
    "family": "Fabaceae (609)",
    "species": "Glycine max (399)"
  },
  "158": {
    "n": 1331,
    "organ": "whole-plant (751)",
    "order": "Poales (1266)",
    "family": "Poaceae (1266)",
    "species": "Zea mays (1148)"
  },
  "159": {
    "n": 4166,
    "organ": "leaf (3114)",
    "order": "Poales (3636)",
    "family": "Poaceae (3636)",
    "species": "Triticum aestivum (3243)"
  },
  "160": {
    "n": 4457,
    "organ": "root (3252)",
    "order": "Asterales (640)",
    "family": "Asteraceae (640)",
    "species": "Ipomoea batatas (517)"
  },
  "161": {
    "n": 2952,
    "organ": "leaf (2553)",
    "order": "Malpighiales (675)",
    "family": "Euphorbiaceae (675)",
    "species": "Manihot esculenta (583)"
  },
  "162": {
    "n": 2100,
    "organ": "leaf (1548)",
    "order": "Solanales (1810)",
    "family": "Solanaceae (1810)",
    "species": "Nicotiana tabacum (1050)"
  },
  "163": {
    "n": 3339,
    "organ": "fruit (1588)",
    "order": "mixed",
    "family": "mixed",
    "species": "Citrus sinensis (933)"
  },
  "164": {
    "n": 4976,
    "organ": "leaf (2042)",
    "order": "Pinales (2356)",
    "family": "Pinaceae (2356)",
    "species": "Ginkgo biloba (447)"
  },
  "165": {
    "n": 2700,
    "organ": "flower (527)",
    "order": "Malpighiales (577)",
    "family": "Salicaceae (528)",
    "species": "Populus x canadensis (209)"
  },
  "166": {
    "n": 1463,
    "organ": "stem (291)",
    "order": "Malpighiales (1208)",
    "family": "Salicaceae (1208)",
    "species": "Populus trichocarpa (344)"
  },
  "167": {
    "n": 1680,
    "organ": "whole-plant (734)",
    "order": "Brassicales (1469)",
    "family": "Brassicaceae (1469)",
    "species": "Arabidopsis thaliana (1366)"
  },
  "168": {
    "n": 2631,
    "organ": "flower (629)",
    "order": "Fabales (1507)",
    "family": "Fabaceae (1507)",
    "species": "Vicia faba (302)"
  },
  "169": {
    "n": 1895,
    "organ": "root (70)",
    "order": "Solanales (1822)",
    "family": "Solanaceae (1822)",
    "species": "Solanum tuberosum (1549)"
  },
  "170": {
    "n": 2027,
    "organ": "leaf (535)",
    "order": "Brassicales (1900)",
    "family": "Brassicaceae (1888)",
    "species": "Arabidopsis thaliana (1189)"
  },
  "171": {
    "n": 2802,
    "organ": "leaf (2003)",
    "order": "Solanales (2602)",
    "family": "Solanaceae (2602)",
    "species": "Solanum lycopersicum (1889)"
  },
  "172": {
    "n": 1601,
    "organ": "whole-plant (432)",
    "order": "Marchantiales (121)",
    "family": "Marchantiaceae (121)",
    "species": "Zygnema circumcarinatum (209)"
  },
  "173": {
    "n": 2619,
    "organ": "leaf (1701)",
    "order": "Poales (1828)",
    "family": "Poaceae (1828)",
    "species": "Panicum virgatum (1421)"
  },
  "174": {
    "n": 2158,
    "organ": "leaf (1222)",
    "order": "Malpighiales (2053)",
    "family": "Salicaceae (2053)",
    "species": "Populus tremula (447)"
  },
  "175": {
    "n": 621,
    "organ": "stem (137)",
    "order": "Malpighiales (451)",
    "family": "Euphorbiaceae (451)",
    "species": "Manihot esculenta (451)"
  },
  "176": {
    "n": 4688,
    "organ": "root (3229)",
    "order": "Fabales (4254)",
    "family": "Fabaceae (4254)",
    "species": "Glycine max (3652)"
  },
  "177": {
    "n": 1961,
    "organ": "flower (743)",
    "order": "Rosales (1868)",
    "family": "Rosaceae (1868)",
    "species": "Prunus persica (311)"
  },
  "178": {
    "n": 1747,
    "organ": "leaf (1057)",
    "order": "Brassicales (1708)",
    "family": "Brassicaceae (1708)",
    "species": "Brassica napus (1191)"
  },
  "179": {
    "n": 2797,
    "organ": "leaf (1952)",
    "order": "Malpighiales (184)",
    "family": "Euphorbiaceae (184)",
    "species": "Manihot esculenta (146)"
  },
  "180": {
    "n": 2882,
    "organ": "flower (760)",
    "order": "mixed",
    "family": "mixed",
    "species": "Dendrobium officinale (345)"
  },
  "181": {
    "n": 3491,
    "organ": "whole-plant (1022)",
    "order": "Brassicales (2924)",
    "family": "Brassicaceae (2922)",
    "species": "Arabidopsis thaliana (2493)"
  },
  "182": {
    "n": 3116,
    "organ": "whole-plant (395)",
    "order": "Poales (6)",
    "family": "Poaceae (6)",
    "species": "Haematococcus lacustris (123)"
  },
  "183": {
    "n": 787,
    "organ": "root (465)",
    "order": "Brassicales (786)",
    "family": "Brassicaceae (786)",
    "species": "Arabidopsis thaliana (745)"
  },
  "184": {
    "n": 2973,
    "organ": "leaf (1775)",
    "order": "Fabales (2017)",
    "family": "Fabaceae (2017)",
    "species": "Medicago sativa (1086)"
  },
  "185": {
    "n": 2243,
    "organ": "leaf (1515)",
    "order": "Caryophyllales (1127)",
    "family": "Amaranthaceae (1127)",
    "species": "Spinacia oleracea (306)"
  },
  "186": {
    "n": 4021,
    "organ": "leaf (890)",
    "order": "Lamiales (393)",
    "family": "Oleaceae (224)",
    "species": "Osmanthus fragrans (255)"
  },
  "187": {
    "n": 1791,
    "organ": "leaf (1468)",
    "order": "Vitales (1656)",
    "family": "Vitaceae (1656)",
    "species": "Vitis vinifera (1299)"
  },
  "188": {
    "n": 2484,
    "organ": "whole-plant (1905)",
    "order": "Marchantiales (2001)",
    "family": "Marchantiaceae (2001)",
    "species": "Marchantia polymorpha (1485)"
  },
  "189": {
    "n": 1375,
    "organ": "seed (901)",
    "order": "Fabales (1045)",
    "family": "Fabaceae (1045)",
    "species": "Glycine max (682)"
  },
  "190": {
    "n": 2814,
    "organ": "leaf (2561)",
    "order": "Poales (2740)",
    "family": "Poaceae (2740)",
    "species": "Zea mays (1957)"
  },
  "191": {
    "n": 1072,
    "organ": "root (363)",
    "order": "Poales (973)",
    "family": "Poaceae (973)",
    "species": "Oryza sativa Japonica Group (311)"
  },
  "192": {
    "n": 2605,
    "organ": "fruit (766)",
    "order": "Vitales (2478)",
    "family": "Vitaceae (2478)",
    "species": "Vitis vinifera (2071)"
  },
  "193": {
    "n": 3022,
    "organ": "leaf (1782)",
    "order": "Brassicales (2544)",
    "family": "Brassicaceae (2544)",
    "species": "Arabidopsis thaliana (2240)"
  },
  "194": {
    "n": 2948,
    "organ": "stem (1395)",
    "order": "Fabales (2584)",
    "family": "Fabaceae (2584)",
    "species": "Glycine max (2150)"
  },
  "195": {
    "n": 2855,
    "organ": "leaf (2219)",
    "order": "Rosales (2552)",
    "family": "Rosaceae (2552)",
    "species": "Malus domestica (401)"
  },
  "196": {
    "n": 3425,
    "organ": "leaf (2501)",
    "order": "Poales (1665)",
    "family": "Poaceae (1665)",
    "species": "Saccharum officinarum (282)"
  },
  "197": {
    "n": 6306,
    "organ": "leaf (4665)",
    "order": "Brassicales (5921)",
    "family": "Brassicaceae (5921)",
    "species": "Arabidopsis thaliana (5596)"
  },
  "198": {
    "n": 2495,
    "organ": "stem (984)",
    "order": "Brassicales (2169)",
    "family": "Brassicaceae (2158)",
    "species": "Brassica napus (1132)"
  },
  "199": {
    "n": 4592,
    "organ": "whole-plant (2705)",
    "order": "Brassicales (4064)",
    "family": "Brassicaceae (4064)",
    "species": "Arabidopsis thaliana (3942)"
  },
  "200": {
    "n": 2586,
    "organ": "cell-culture (714)",
    "order": "Brassicales (1287)",
    "family": "Brassicaceae (1287)",
    "species": "Arabidopsis thaliana (1212)"
  },
  "201": {
    "n": 1863,
    "organ": "root (1173)",
    "order": "Apiales (75)",
    "family": "Apiaceae (75)",
    "species": "Panax ginseng (807)"
  },
  "202": {
    "n": 1251,
    "organ": "root (505)",
    "order": "Poales (1166)",
    "family": "Poaceae (1166)",
    "species": "Triticum aestivum (660)"
  },
  "203": {
    "n": 1486,
    "organ": "leaf (602)",
    "order": "Poales (716)",
    "family": "Poaceae (716)",
    "species": "Zea mays (208)"
  },
  "204": {
    "n": 1691,
    "organ": "leaf (387)",
    "order": "Malpighiales (350)",
    "family": "Malvaceae (319)",
    "species": "Theobroma cacao (319)"
  },
  "205": {
    "n": 1388,
    "organ": "root (942)",
    "order": "Rosales (1326)",
    "family": "Rosaceae (1326)",
    "species": "Malus domestica (437)"
  },
  "206": {
    "n": 1488,
    "organ": "whole-plant (152)",
    "order": "Marchantiales (1)",
    "family": "Marchantiaceae (1)",
    "species": "Chlamydomonas reinhardtii (175)"
  },
  "207": {
    "n": 2527,
    "organ": "fruit (1242)",
    "order": "Cucurbitales (2268)",
    "family": "Cucurbitaceae (2268)",
    "species": "Citrullus lanatus (704)"
  },
  "208": {
    "n": 2292,
    "organ": "flower (1053)",
    "order": "Poales (2160)",
    "family": "Poaceae (2160)",
    "species": "Triticum aestivum (1370)"
  },
  "209": {
    "n": 1231,
    "organ": "seed (858)",
    "order": "Brassicales (1031)",
    "family": "Brassicaceae (1028)",
    "species": "Arabidopsis thaliana (681)"
  },
  "210": {
    "n": 2159,
    "organ": "fruit (721)",
    "order": "Solanales (2101)",
    "family": "Solanaceae (2101)",
    "species": "Solanum lycopersicum (1609)"
  },
  "211": {
    "n": 2008,
    "organ": "fruit (918)",
    "order": "Rosales (1950)",
    "family": "Rosaceae (1950)",
    "species": "Fragaria x ananassa (819)"
  },
  "212": {
    "n": 1555,
    "organ": "flower (1219)",
    "order": "Ericales (111)",
    "family": "Theaceae (111)",
    "species": "Amborella trichopoda (55)"
  },
  "213": {
    "n": 2181,
    "organ": "leaf (1159)",
    "order": "Caryophyllales (852)",
    "family": "Amaranthaceae (852)",
    "species": "Chenopodium quinoa (314)"
  },
  "214": {
    "n": 2956,
    "organ": "fruit (1807)",
    "order": "Rosales (2562)",
    "family": "Rosaceae (2562)",
    "species": "Malus domestica (1430)"
  },
  "215": {
    "n": 2302,
    "organ": "leaf (1913)",
    "order": "Poales (2241)",
    "family": "Poaceae (2241)",
    "species": "Zea mays (2117)"
  },
  "216": {
    "n": 1616,
    "organ": "stem (288)",
    "order": "Pinales (1098)",
    "family": "Pinaceae (1098)",
    "species": "Picea abies (255)"
  },
  "217": {
    "n": 2112,
    "organ": "leaf (1363)",
    "order": "Solanales (482)",
    "family": "Solanaceae (482)",
    "species": "Solanum lycopersicum (214)"
  },
  "218": {
    "n": 7718,
    "organ": "stem (2087)",
    "order": "Brassicales (6761)",
    "family": "Brassicaceae (6740)",
    "species": "Arabidopsis thaliana (5861)"
  },
  "219": {
    "n": 4053,
    "organ": "leaf (2274)",
    "order": "Poales (3991)",
    "family": "Poaceae (3991)",
    "species": "Zea mays (1713)"
  },
  "220": {
    "n": 1405,
    "organ": "seed (452)",
    "order": "Poales (1255)",
    "family": "Poaceae (1255)",
    "species": "Oryza sativa (694)"
  },
  "221": {
    "n": 1864,
    "organ": "leaf (1505)",
    "order": "mixed",
    "family": "mixed",
    "species": "Citrus sinensis (717)"
  },
  "222": {
    "n": 896,
    "organ": "leaf (313)",
    "order": "Poales (337)",
    "family": "Poaceae (337)",
    "species": "Setaria viridis (257)"
  },
  "223": {
    "n": 3090,
    "organ": "root (2607)",
    "order": "Malvales (2915)",
    "family": "Malvaceae (2915)",
    "species": "Gossypium hirsutum (2438)"
  },
  "224": {
    "n": 1584,
    "organ": "whole-plant (1033)",
    "order": "Funariales (886)",
    "family": "Funariaceae (886)",
    "species": "Physcomitrium patens (882)"
  },
  "225": {
    "n": 2166,
    "organ": "fruit (1455)",
    "order": "Rosales (2069)",
    "family": "Rosaceae (2069)",
    "species": "Prunus persica (1167)"
  },
  "226": {
    "n": 3193,
    "organ": "leaf (1833)",
    "order": "Solanales (408)",
    "family": "Solanaceae (408)",
    "species": "Citrus sinensis (235)"
  },
  "227": {
    "n": 1600,
    "organ": "root (1001)",
    "order": "Fabales (1108)",
    "family": "Fabaceae (1108)",
    "species": "Glycine max (299)"
  },
  "228": {
    "n": 2985,
    "organ": "root (2224)",
    "order": "Poales (2625)",
    "family": "Poaceae (2625)",
    "species": "Zea mays (2561)"
  },
  "229": {
    "n": 2126,
    "organ": "root (1211)",
    "order": "Lamiales (165)",
    "family": "Pedaliaceae (153)",
    "species": "Sesamum indicum (153)"
  },
  "230": {
    "n": 1266,
    "organ": "leaf (1138)",
    "order": "Malpighiales (751)",
    "family": "Salicaceae (626)",
    "species": "Salix purpurea (608)"
  },
  "231": {
    "n": 2470,
    "organ": "root (1687)",
    "order": "Poales (2173)",
    "family": "Poaceae (2173)",
    "species": "Hordeum vulgare (826)"
  },
  "232": {
    "n": 2544,
    "organ": "fruit (1129)",
    "order": "Solanales (2069)",
    "family": "Solanaceae (2069)",
    "species": "Capsicum annuum (674)"
  },
  "233": {
    "n": 1664,
    "organ": "flower (807)",
    "order": "Poales (1664)",
    "family": "Poaceae (1664)",
    "species": "Hordeum vulgare subsp. vulgare (1382)"
  },
  "234": {
    "n": 2945,
    "organ": "leaf (739)",
    "order": "Brassicales (1950)",
    "family": "Brassicaceae (1949)",
    "species": "Arabidopsis thaliana (1689)"
  },
  "235": {
    "n": 1082,
    "organ": "leaf (1029)",
    "order": "Poales (1042)",
    "family": "Poaceae (1042)",
    "species": "Brachypodium distachyon (1009)"
  },
  "236": {
    "n": 1051,
    "organ": "leaf (615)",
    "order": "Poales (1051)",
    "family": "Poaceae (1051)",
    "species": "Zea mays (1028)"
  },
  "237": {
    "n": 2024,
    "organ": "leaf (571)",
    "order": "Brassicales (705)",
    "family": "Brassicaceae (705)",
    "species": "Arabidopsis thaliana (670)"
  },
  "238": {
    "n": 2999,
    "organ": "seed (1561)",
    "order": "Ericales (385)",
    "family": "Theaceae (385)",
    "species": "Camellia oleifera (302)"
  },
  "239": {
    "n": 1589,
    "organ": "leaf (1044)",
    "order": "Poales (1539)",
    "family": "Poaceae (1539)",
    "species": "Oryza sativa (887)"
  },
  "240": {
    "n": 2365,
    "organ": "leaf (1628)",
    "order": "Fabales (230)",
    "family": "Fabaceae (230)",
    "species": "Linum usitatissimum (69)"
  },
  "241": {
    "n": 2141,
    "organ": "fruit (947)",
    "order": "Poales (2095)",
    "family": "Poaceae (2095)",
    "species": "Zea mays (2064)"
  },
  "242": {
    "n": 2567,
    "organ": "flower (1062)",
    "order": "Poales (2294)",
    "family": "Poaceae (2294)",
    "species": "Oryza sativa (1419)"
  },
  "243": {
    "n": 1678,
    "organ": "stem (554)",
    "order": "Malvales (1409)",
    "family": "Malvaceae (1409)",
    "species": "Gossypium hirsutum (1012)"
  },
  "244": {
    "n": 2895,
    "organ": "leaf (2212)",
    "order": "Solanales (2459)",
    "family": "Solanaceae (2459)",
    "species": "Solanum tuberosum (965)"
  },
  "245": {
    "n": 4258,
    "organ": "root (3201)",
    "order": "Fabales (3408)",
    "family": "Fabaceae (3408)",
    "species": "Medicago truncatula (2000)"
  },
  "246": {
    "n": 1734,
    "organ": "seed (488)",
    "order": "Brassicales (1597)",
    "family": "Brassicaceae (1591)",
    "species": "Arabidopsis thaliana (1082)"
  },
  "247": {
    "n": 1340,
    "organ": "root (1067)",
    "order": "Malpighiales (1253)",
    "family": "Salicaceae (1253)",
    "species": "Populus trichocarpa (341)"
  },
  "248": {
    "n": 1675,
    "organ": "leaf (1104)",
    "order": "Asterales (893)",
    "family": "Asteraceae (893)",
    "species": "Lactuca sativa (226)"
  },
  "249": {
    "n": 2140,
    "organ": "leaf (1913)",
    "order": "Poales (1944)",
    "family": "Poaceae (1944)",
    "species": "Sorghum bicolor (1670)"
  }
}